saturnin/sdk/__about__.py
saturnin/sdk/__init__.py
saturnin/sdk/commands/__init__.py
saturnin/sdk/commands/recipes.py
saturnin_sdk-0.10.0.dist-info/METADATA
saturnin_sdk-0.10.0.dist-info/WHEEL
saturnin_sdk-0.10.0.dist-info/entry_points.txt
saturnin_sdk-0.10.0.dist-info/licenses/LICENSE
saturnin_sdk-0.10.0.dist-info/RECORD
