Metadata-Version: 2.4
Name: saturnin-sdk
Version: 0.10.0
Summary: SDK for Saturnin (A Firebird Butler Development Platform for Python)
Project-URL: Home, https://github.com/FirebirdSQL/saturnin-sdk
Project-URL: Documentation, https://saturnin-sdk.rtfd.io
Project-URL: Issues, https://github.com/FirebirdSQL/saturnin-sdk/issues
Project-URL: Funding, https://github.com/sponsors/pcisar
Project-URL: Source, https://github.com/FirebirdSQL/saturnin-sdk
Author-email: Pavel Cisar <pcisar@users.sourceforge.net>
License: MIT License
License-File: LICENSE
Keywords: Butler,Firebird,SDK,Saturnin,Services,ZeroMQ
Classifier: Development Status :: 4 - Beta
Classifier: Intended Audience :: Developers
Classifier: License :: OSI Approved :: MIT License
Classifier: Operating System :: MacOS
Classifier: Operating System :: Microsoft :: Windows
Classifier: Operating System :: POSIX :: Linux
Classifier: Programming Language :: Python :: 3 :: Only
Classifier: Programming Language :: Python :: 3.11
Classifier: Programming Language :: Python :: 3.12
Classifier: Programming Language :: Python :: 3.13
Classifier: Topic :: Software Development :: Libraries
Classifier: Topic :: Software Development :: Libraries :: Application Frameworks
Classifier: Topic :: Software Development :: Object Brokering
Requires-Python: >=3.11
Requires-Dist: saturnin==0.10.0
